win32material/__init__.py
win32material/win32material.py
win32material-1.0.7.dist-info/LICENSE
win32material-1.0.7.dist-info/METADATA
win32material-1.0.7.dist-info/WHEEL
win32material-1.0.7.dist-info/top_level.txt
win32material-1.0.7.dist-info/RECORD
