Metadata-Version: 2.2
Name: win32material
Version: 1.0.7
Summary: Apply some window effects to the Win32 Applications
Home-page: https://github.com/littlewhitecloud/win32material
Author: littlewhitecloud
License-File: LICENSE
Dynamic: author
Dynamic: description
Dynamic: description-content-type
Dynamic: home-page
Dynamic: summary
